colcon_parallel_executor/__init__.py
colcon_parallel_executor/event/__init__.py
colcon_parallel_executor/event/executor.py
colcon_parallel_executor/event_handler/__init__.py
colcon_parallel_executor/event_handler/parallel_status.py
colcon_parallel_executor/executor/__init__.py
colcon_parallel_executor/executor/parallel.py
colcon_parallel_executor-0.4.0.dist-info/LICENSE
colcon_parallel_executor-0.4.0.dist-info/METADATA
colcon_parallel_executor-0.4.0.dist-info/WHEEL
colcon_parallel_executor-0.4.0.dist-info/entry_points.txt
colcon_parallel_executor-0.4.0.dist-info/top_level.txt
colcon_parallel_executor-0.4.0.dist-info/zip-safe
colcon_parallel_executor-0.4.0.dist-info/RECORD
