Metadata-Version: 2.1
Name: colcon-parallel-executor
Version: 0.4.0
Summary: Extension for colcon to process packages in parallel.
Home-page: https://colcon.readthedocs.io
Author: Dirk Thomas
Author-email: web@dirk-thomas.net
Maintainer: Dirk Thomas
Maintainer-email: web@dirk-thomas.net
License: Apache License, Version 2.0
Project-URL: Changelog, https://github.com/colcon/colcon-parallel-executor/milestones?direction=desc&sort=due_date&state=closed
Project-URL: GitHub, https://github.com/colcon/colcon-parallel-executor/
Keywords: colcon
Platform: UNKNOWN
Classifier: Development Status :: 3 - Alpha
Classifier: Environment :: Plugins
Classifier: Intended Audience :: Developers
Classifier: License :: OSI Approved :: Apache Software License
Classifier: Operating System :: MacOS
Classifier: Operating System :: Microsoft :: Windows
Classifier: Operating System :: POSIX
Classifier: Programming Language :: Python
Classifier: Topic :: Software Development :: Build Tools
Requires-Python: >=3.6
Provides-Extra: test
License-File: LICENSE
